wendigo/__init__.py
wendigo/core.py
wendigo/exceptions.py
wendigo/logger.py
wendigo/warnings.py
wendigo/wendigo.py
wendigo/application/__init__.py
wendigo/application/dll.py
wendigo/bin/x64/Application.dll
wendigo/bin/x64/Device.dll
wendigo/bin/x64/Process.dll
wendigo/bin/x64/Screen.dll
wendigo/device/__init__.py
wendigo/device/core.py
wendigo/device/dll.py
wendigo/device/event_dispatcher.py
wendigo/device/event_imitator.py
wendigo/device/event_simulator.py
wendigo/process/__init__.py
wendigo/process/dll.py
wendigo/process/time_keeper.py
wendigo/screen/__init__.py
wendigo/screen/dll.py
wendigo/screen/form_controller.py
wendigo/screen/target_form.py
wendigo/screen/target_marker.py
wendigo/screen/target_seeker.py
wendigo/screen/text_reader.py
wendigo/setup/__init__.py
wendigo/setup/check.py
wendigo/setup/cleanup.py
wendigo/setup/import_.py
wendigo/system/__init__.py
wendigo/system/color.py
wendigo/system/keys.py
Wendigo-0.1.1.dist-info/LICENSE
Wendigo-0.1.1.dist-info/METADATA
Wendigo-0.1.1.dist-info/WHEEL
Wendigo-0.1.1.dist-info/top_level.txt
Wendigo-0.1.1.dist-info/RECORD
