Metadata-Version: 2.1
Name: Wendigo
Version: 0.1.1
Summary: Wendigo is a RPA library for Windows (64 bit).
Home-page: https://github.com/medmsyk/wendigopy
Author: medmsyk
Author-email: michael.lee.maeda@gmail.com
License: Apache License 2.0
Platform: UNKNOWN
Requires-Dist: opencv-python (~=4.9)
Requires-Dist: pillow (~=10.3)
Requires-Dist: pytesseract (~=0.3)
Requires-Dist: pythonnet (~=3.0)
